sappl/__init__.py
sappl/augmentations.py
sappl/feature_extraction.py
sappl/io.py
sappl/processor.py
sappl/transform.py
sappl/utils.py
sappl-0.1.3.dist-info/METADATA
sappl-0.1.3.dist-info/WHEEL
sappl-0.1.3.dist-info/top_level.txt
sappl-0.1.3.dist-info/RECORD
