Metadata-Version: 2.1
Name: sappl
Version: 0.1.3
Summary: Simple Audio Pre-Processing Library for deep learning audio applications
Home-page: https://github.com/MorenoLaQuatra/sappl
Author: Moreno La Quatra
Author-email: moreno.laquatra@gmail.com
Classifier: Programming Language :: Python :: 3
Classifier: License :: OSI Approved :: MIT License
Classifier: Operating System :: OS Independent
Classifier: Topic :: Multimedia :: Sound/Audio :: Analysis
Classifier: Intended Audience :: Science/Research
Classifier: Natural Language :: English
Requires-Python: >=3.6
Requires-Dist: numpy
Requires-Dist: librosa
Requires-Dist: soundfile
Requires-Dist: pydub
Requires-Dist: torch
Requires-Dist: ffmpeg-python
